LICENSE
README.md
setup.py
scRare/__init__.py
scRare/scRare_IO.py
scRare/scRare_classifier.py
scRare/score_functions.py
scRare/weightsampling.py
scRare.egg-info/PKG-INFO
scRare.egg-info/SOURCES.txt
scRare.egg-info/dependency_links.txt
scRare.egg-info/top_level.txt